MaybeDont-0.1.0.dist-info/DESCRIPTION.rst
MaybeDont-0.1.0.dist-info/METADATA
MaybeDont-0.1.0.dist-info/RECORD
MaybeDont-0.1.0.dist-info/WHEEL
MaybeDont-0.1.0.dist-info/metadata.json
MaybeDont-0.1.0.dist-info/top_level.txt
maybedont/__init__.py
maybedont/predict.py
maybedont/scrapy_middleware.py
maybedont/utils.py
