Metadata-Version: 2.0
Name: MaybeDont
Version: 0.1.0
Summary: A component that tried to avoid downloading duplite content
Home-page: https://github.com/TeamHG-Memex/MaybeDont
Author: Konstantin Lopuhin
Author-email: kostia.lopuhin@gmail.com
License: MIT
Platform: UNKNOWN
Classifier: Development Status :: 3 - Alpha
Classifier: Topic :: Internet :: WWW/HTTP :: Indexing/Search
Classifier: License :: OSI Approved :: MIT License
Classifier: Programming Language :: Python
Classifier: Programming Language :: Python :: 2
Classifier: Programming Language :: Python :: 2.7
Classifier: Programming Language :: Python :: 3
Classifier: Programming Language :: Python :: 3.3
Classifier: Programming Language :: Python :: 3.4
Classifier: Programming Language :: Python :: 3.5
Requires-Dist: datasketch (>=0.2.0)
Requires-Dist: six
